Metadata-Version: 2.1
Name: bumbo-mikhin
Version: 0.0.2
Summary: Bumbo mikhin Python Web Framework built for learning purposes.
Author: dimamikhin
Author-email: zobzagfra7@cobmk.com
License: MIT
Classifier: Programming Language :: Python :: 3.6
Requires-Python: >=3.6.0
Requires-Dist: Jinja2 ==3.1.2
Requires-Dist: parse ==1.19.0
Requires-Dist: requests ==2.31.0
Requires-Dist: requests-wsgi-adapter ==0.4.1
Requires-Dist: WebOb ==1.8.7
Requires-Dist: whitenoise ==6.4.0
